asocksimap/__init__.py
asocksimap/version.py
asocksimap-1.0.4.dist-info/LICENSE
asocksimap-1.0.4.dist-info/METADATA
asocksimap-1.0.4.dist-info/WHEEL
asocksimap-1.0.4.dist-info/top_level.txt
asocksimap-1.0.4.dist-info/RECORD
