Metadata-Version: 2.1
Name: asocksimap
Version: 1.0.4
Summary: Connect to IMAP through Socks using Python asyncio
Home-page: https://github.com/optinsoft/asocksimap
Author: optinsoft
Author-email: optinsoft@gmail.com
Keywords: socks,imap,asyncio
License-File: LICENSE
Requires-Dist: aioimaplib >=1.0.1
Requires-Dist: aiosocks >=0.2.6
